lazymedia/__init__.py
lazymedia/castbox.py
lazymedia/ixigua.py
lazymedia/youtube.py
lazymedia-0.0.3.dist-info/METADATA
lazymedia-0.0.3.dist-info/WHEEL
lazymedia-0.0.3.dist-info/top_level.txt
lazymedia-0.0.3.dist-info/RECORD
