Metadata-Version: 2.1
Name: lazymedia
Version: 0.0.3
Home-page: https://gitee.com/ZeroSeeker/lazymedia
Author: ZeroSeeker
Author-email: zeroseeker@foxmail.com
Classifier: Programming Language :: Python :: 3
Classifier: Operating System :: OS Independent
Requires-Dist: lazysdk (>=0.1.1)
